nanokvm/__init__.py
nanokvm/client.py
nanokvm/models.py
nanokvm/py.typed
nanokvm/ssh_client.py
nanokvm/utils.py
nanokvm-0.2.0.dist-info/licenses/LICENSE
nanokvm-0.2.0.dist-info/METADATA
nanokvm-0.2.0.dist-info/WHEEL
nanokvm-0.2.0.dist-info/top_level.txt
nanokvm-0.2.0.dist-info/RECORD
