Metadata-Version: 2.4
Name: nanokvm
Version: 0.2.0
Summary: Async client for NanoKVM devices.
Author-email: puddly <puddly3@gmail.com>
License: Apache-2.0
Project-URL: repository, https://github.com/puddly/python-nanokvm
Requires-Python: >=3.11
License-File: LICENSE
Requires-Dist: aiohttp
Requires-Dist: cryptography
Requires-Dist: yarl
Requires-Dist: pillow
Requires-Dist: pydantic
Requires-Dist: paramiko
Provides-Extra: testing
Requires-Dist: tomli; extra == "testing"
Requires-Dist: coverage[toml]; extra == "testing"
Requires-Dist: pytest; extra == "testing"
Requires-Dist: pytest-xdist; extra == "testing"
Requires-Dist: pytest-asyncio; extra == "testing"
Requires-Dist: pytest-cov; extra == "testing"
Requires-Dist: pytest-timeout; extra == "testing"
Requires-Dist: aioresponses; extra == "testing"
Dynamic: license-file
